s3_site_cache_optimizer/__init__.py
s3_site_cache_optimizer/optimize.py
s3_site_cache_optimizer-0.8.2.dist-info/LICENSE
s3_site_cache_optimizer-0.8.2.dist-info/METADATA
s3_site_cache_optimizer-0.8.2.dist-info/WHEEL
s3_site_cache_optimizer-0.8.2.dist-info/entry_points.txt
s3_site_cache_optimizer-0.8.2.dist-info/top_level.txt
s3_site_cache_optimizer-0.8.2.dist-info/RECORD
