Metadata-Version: 2.1
Name: s3-site-cache-optimizer
Version: 0.8.2
Summary: Optimize a static website before uploading to S3
Home-page: https://github.com/novemberfiveco/s3-site-cache-optimizer
Author: Ruben Van den Bossche, Matteo De Wint
Author-email: ruben@novemberfive.co, matteo@novemberfive.co
License: MIT
Platform: UNKNOWN
Requires-Dist: boto
